eovsapy/StringUtil.py
eovsapy/__init__.py
eovsapy/astronet.py
eovsapy/attncal.py
eovsapy/autocorrect_tp.py
eovsapy/azel_current_spikes.py
eovsapy/cal_calendar.py
eovsapy/cal_header.py
eovsapy/calibration.py
eovsapy/calwidget.py
eovsapy/chan_info_52.py
eovsapy/chan_util_52.py
eovsapy/chan_util_bc.py
eovsapy/coord_conv.py
eovsapy/daily_xsp.py
eovsapy/dbutil.py
eovsapy/disk_conv.py
eovsapy/dump_tsys.py
eovsapy/eovsa_array.py
eovsapy/eovsa_cat.py
eovsapy/eovsa_fits.py
eovsapy/eovsa_lst.py
eovsapy/eovsa_tracktable.py
eovsapy/eovsa_visibility.py
eovsapy/feed_rot_simulation.py
eovsapy/flare_spec.py
eovsapy/gaincal2.py
eovsapy/get_sat_info.py
eovsapy/get_xy_corr.py
eovsapy/goes.py
eovsapy/pipeline_allday_fits.py
eovsapy/pipeline_cal.py
eovsapy/read_idb.py
eovsapy/read_xml2.py
eovsapy/readbsc.py
eovsapy/readvla.py
eovsapy/rstn.py
eovsapy/solpnt.py
eovsapy/sqlutil.py
eovsapy/sun_pos.py
eovsapy/tooltip.py
eovsapy/udb_util.py
eovsapy/util.py
eovsapy/whatup.py
eovsapy/whenup.py
eovsapy/xspfits2.py
eovsapy/SourceCat/BrightStarCatalog.txt
eovsapy/SourceCat/bsc5.dat
eovsapy/SourceCat/mysql_tables.txt
eovsapy/SourceCat/mysql_tables_old.txt
eovsapy/SourceCat/starburst.srclist
eovsapy/SourceCat/totalpower.srclist
eovsapy/SourceCat/vla_calibrator_list.txt
eovsapy/shellScript/add_yrdir.csh
eovsapy/shellScript/crontablist.sh
eovsapy/shellScript/daily_xsp.sh
eovsapy/shellScript/pipeline.sh
eovsapy/shellScript/pipeline1.csh
eovsapy/shellScript/pipeline2.csh
eovsapy/shellScript/pipeline_allday_fits.sh
eovsapy/shellScript/pipeline_compress.sh
eovsapy/shellScript/pipeline_fdimg.sh
eovsapy/shellScript/pipeline_plt.sh
eovsapy/shellScript/pipeline_plt_movie.sh
obsolete/setup.py
eovsapy-0.1.0.1.dist-info/LICENSE.rst
eovsapy-0.1.0.1.dist-info/METADATA
eovsapy-0.1.0.1.dist-info/WHEEL
eovsapy-0.1.0.1.dist-info/top_level.txt
eovsapy-0.1.0.1.dist-info/RECORD
