Metadata-Version: 2.1
Name: eovsapy
Version: 0.1.0.1
Summary: Python code and files for Expanded Owens Valley Solar Array
Author-email: The EOVSA team <sijie.yu@njit.edu>
License: Copyright (c) 2017-2023 The EOVSAPY developers
Project-URL: Homepage, https://github.com/ovro-eovsa/eovsapy
Project-URL: Repository, https://github.com/ovro-eovsa/eovsapy
Keywords: solar physics,solar,science,sun,radio,miriad
Classifier: Development Status :: 5 - Production/Stable
Classifier: Intended Audience :: Science/Research
Classifier: License :: OSI Approved :: BSD License
Classifier: Natural Language :: English
Classifier: Operating System :: OS Independent
Classifier: Programming Language :: Python
Classifier: Programming Language :: Python :: 3.6
Classifier: Programming Language :: Python :: 3.8
Classifier: Topic :: Scientific/Engineering :: Physics
Requires-Python: >=3.6
License-File: LICENSE.rst
Requires-Dist: aipy-eovsa
Requires-Dist: astropy
Requires-Dist: attrs
Requires-Dist: certifi
Requires-Dist: decorator
Requires-Dist: ephem
Requires-Dist: importlib-metadata
Requires-Dist: importlib-resources
Requires-Dist: matplotlib >=3.6
Requires-Dist: mysql-connector-python
Requires-Dist: numpy
Requires-Dist: pandas
Requires-Dist: pyodbc
Requires-Dist: pyparsing
Requires-Dist: python-dateutil
Requires-Dist: requests
Requires-Dist: scipy
Requires-Dist: six
Requires-Dist: sunpy
Requires-Dist: tk
Requires-Dist: tqdm
Requires-Dist: urllib3
Provides-Extra: dev
Requires-Dist: ipython ; extra == 'dev'
Requires-Dist: ipython-genutils ; extra == 'dev'
Requires-Dist: PyQt5 ; extra == 'dev'
Requires-Dist: PyQt5-Qt5 ; extra == 'dev'
Requires-Dist: PyQt5-sip ; extra == 'dev'
